django_icase-0.1.1.dist-info/DESCRIPTION.rst
django_icase-0.1.1.dist-info/METADATA
django_icase-0.1.1.dist-info/metadata.json
django_icase-0.1.1.dist-info/RECORD
django_icase-0.1.1.dist-info/top_level.txt
django_icase-0.1.1.dist-info/WHEEL
icase/__init__.py
icase/middleware.py
icase/models.py
icase/views.py
