Metadata-Version: 2.0
Name: django-icase
Version: 0.1.1
Summary: A few tools for helping with case-insensitvity in Django URLs.
Home-page: https://github.com/bennylope/django-icase
Author: Ben Lopatin
Author-email: ben@wellfire.co
License: BSD
Keywords: django-icase
Platform: UNKNOWN
Classifier: Development Status :: 2 - Pre-Alpha
Classifier: Framework :: Django
Classifier: Intended Audience :: Developers
Classifier: License :: OSI Approved :: BSD License
Classifier: Natural Language :: English
Classifier: Programming Language :: Python :: 2
Classifier: Programming Language :: Python :: 2.6
Classifier: Programming Language :: Python :: 2.7
Classifier: Programming Language :: Python :: 3
Classifier: Programming Language :: Python :: 3.3
